[
  {
    "_id": "Водитель",
    "max": 198173,
    "min": 20487,
    "avg": 109632.15789473684
  },
  {
    "_id": "Строитель",
    "max": 196476,
    "min": 22484,
    "avg": 109628.58139534884
  },
  {
    "_id": "Менеджер",
    "max": 196601,
    "min": 20603,
    "avg": 109845.61643835617
  },
  {
    "_id": "Косметолог",
    "max": 199262,
    "min": 20336,
    "avg": 117722.18292682926
  },
  {
    "_id": "Инженер",
    "max": 199938,
    "min": 20724,
    "avg": 109341.56756756757
  },
  {
    "_id": "Бухгалтер",
    "max": 198370,
    "min": 27227,
    "avg": 115403.89393939394
  },
  {
    "_id": "Повар",
    "max": 199343,
    "min": 20301,
    "avg": 109487.86419753087
  },
  {
    "_id": "Программист",
    "max": 197182,
    "min": 21862,
    "avg": 112185.27956989247
  },
  {
    "_id": "Архитектор",
    "max": 199107,
    "min": 23956,
    "avg": 111124.52
  },
  {
    "_id": "Продавец",
    "max": 196610,
    "min": 21286,
    "avg": 114128.6
  },
  {
    "_id": "IT-специалист",
    "max": 199177,
    "min": 23667,
    "avg": 112311.15853658537
  },
  {
    "_id": "Учитель",
    "max": 199737,
    "min": 20424,
    "avg": 121282.07142857143
  },
  {
    "_id": "Врач",
    "max": 199232,
    "min": 24611,
    "avg": 113167.34722222222
  },
  {
    "_id": "Оператор call-центра",
    "max": 197740,
    "min": 22371,
    "avg": 110986.07692307692
  },
  {
    "_id": "Медсестра",
    "max": 198095,
    "min": 25759,
    "avg": 117022.48
  },
  {
    "_id": "Психолог",
    "max": 193167,
    "min": 24737,
    "avg": 100074.93589743589
  }
]